eschallot/__init__.py
eschallot/material_data/Ag_palik.txt
eschallot/material_data/Ag_yang.txt
eschallot/material_data/Air.txt
eschallot/material_data/Al2O3_Boidin.txt
eschallot/material_data/Al2O3_li.txt
eschallot/material_data/Au_JC.txt
eschallot/material_data/BaF2_final.txt
eschallot/material_data/BaSO4_li.txt
eschallot/material_data/CaCO3_li.txt
eschallot/material_data/CeO2_temp.txt
eschallot/material_data/Dielectric.txt
eschallot/material_data/HfO2_Al_Kuhaili.txt
eschallot/material_data/MgO.txt
eschallot/material_data/PDMS_lossless.txt
eschallot/material_data/PMMA.txt
eschallot/material_data/SU8_2000_vis_lossless.txt
eschallot/material_data/Si3N4_MIR.txt
eschallot/material_data/Si3N4_lossless.txt
eschallot/material_data/SiO2_bulk.txt
eschallot/material_data/Si_Schinke.txt
eschallot/material_data/Si_amorphous.txt
eschallot/material_data/TiO2_Sarkar.txt
eschallot/material_data/TiO2_Siefke.txt
eschallot/material_data/ZrO2_li.txt
eschallot/material_data/__init__.py
eschallot/mie/__init__.py
eschallot/mie/simulate_particle.py
eschallot/mie/special_functions.py
eschallot/mie/tmm_mie.py
eschallot/montecarlo/__init__.py
eschallot/montecarlo/interface_subroutine.py
eschallot/montecarlo/monte_carlo_BSDF.py
eschallot/montecarlo/propagation_subroutine.py
eschallot/montecarlo/snell.py
eschallot/optimization/__init__.py
eschallot/optimization/cost_gradients.py
eschallot/optimization/topology_optimization.py
eschallot/util/__init__.py
eschallot/util/read_mat_data.py
eschallot/util/read_txt.py
eschallot-0.5.0.dist-info/LICENSE
eschallot-0.5.0.dist-info/METADATA
eschallot-0.5.0.dist-info/WHEEL
eschallot-0.5.0.dist-info/top_level.txt
eschallot-0.5.0.dist-info/RECORD
