Metadata-Version: 2.2
Name: eschallot
Version: 0.5.0
Summary: Optimization tool for light-scattering multi-shell spherical particles.
Home-page: https://github.com/apmd-lab/Eschallot
Author: Seokhwan Min
Author-email: petermsh513@gmail.com
Classifier: Development Status :: 4 - Beta
Classifier: Intended Audience :: Science/Research
Classifier: Programming Language :: Python :: 3
Classifier: License :: OSI Approved :: GNU General Public License v3 (GPLv3)
Classifier: Operating System :: Unix
Classifier: Topic :: Scientific/Engineering :: Physics
License-File: LICENSE
Dynamic: author
Dynamic: author-email
Dynamic: classifier
Dynamic: description
Dynamic: description-content-type
Dynamic: home-page
Dynamic: summary
